ManufacturingNet/__init__.py
ManufacturingNet/datasets/__init__.py
ManufacturingNet/datasets/datasets.py
ManufacturingNet/featurization/__init__.py
ManufacturingNet/featurization/featurization.py
ManufacturingNet/models/CNN.py
ManufacturingNet/models/CNN2DImage.py
ManufacturingNet/models/CNN3D.py
ManufacturingNet/models/CNN_LSTM_Default.py
ManufacturingNet/models/DNN.py
ManufacturingNet/models/LSTM_Default.py
ManufacturingNet/models/__init__.py
ManufacturingNet/models/alexnet.py
ManufacturingNet/models/all_classification_models.py
ManufacturingNet/models/all_regression_models.py
ManufacturingNet/models/densenet.py
ManufacturingNet/models/googlenet.py
ManufacturingNet/models/linear_regression.py
ManufacturingNet/models/logistic_regression.py
ManufacturingNet/models/mobilenet.py
ManufacturingNet/models/random_forest.py
ManufacturingNet/models/resnet.py
ManufacturingNet/models/svm.py
ManufacturingNet/models/transformer.py
ManufacturingNet/models/vgg.py
ManufacturingNet/models/vit.py
ManufacturingNet/models/xgb.py
ManufacturingNet/preprocessing/__init__.py
ManufacturingNet/preprocessing/signal_preprocessing.py
DeepManufacturing-0.0.7.dist-info/LICENSE.txt
DeepManufacturing-0.0.7.dist-info/METADATA
DeepManufacturing-0.0.7.dist-info/WHEEL
DeepManufacturing-0.0.7.dist-info/top_level.txt
DeepManufacturing-0.0.7.dist-info/RECORD
