Metadata-Version: 2.1
Name: DeepManufacturing
Version: 0.0.7
Summary: AI and Machine Learning for manufacturing related datasets
Author: Amir Barati Farimani
Author-email: barati@andrew.cmu.edu
License: MIT
Classifier: Programming Language :: Python :: 3
Classifier: Programming Language :: Python :: 3.5
Classifier: Programming Language :: Python :: 3.6
Classifier: Programming Language :: Python :: 3.7
Classifier: Programming Language :: Python :: 3.8
Classifier: Programming Language :: Python :: 3 :: Only
Classifier: Intended Audience :: Education
Requires-Python: >=3.5, <4
License-File: LICENSE.txt
Requires-Dist: sklearn
Requires-Dist: matplotlib
Requires-Dist: xgboost
Requires-Dist: scikit-learn
Requires-Dist: timm
Requires-Dist: Pillow
